{
        "nbTrackables": 3,
        "trackable 0":{
                "type": 1,
                "data":{
                        "url": "FiducialMarkerA",
                        "transform3D": [
                                1.0, 0.0, 0.0, 0.0,
                                0.0, 1.0, 0.0, 0.0,
                                0.0, 0.0, 1.0, 0.0,
                                0.0, 0.0, 0.0, 1.0
                        ],
                        "size": {
                                "width": 0.185,
                                "height": 0.185
                        },
                        "pattern": [
                                0,0,0,0,1,1,
                                1,0,1,1,1,1,
                                1,0,1,1,1,0,
                                1,0,0,0,1,1,
                                1,0,0,0,1,0,
                                0,1,0,0,0,1
                        ]
                }
        },
        "trackable 1":{
                "type": 1,
                "data":{
                        "url": "FiducialMarkerB",
                        "transform3D": [
                                1.0, 0.0, 0.0, 0.0,
                                0.0, 1.0, 0.0, 0.0,
                                0.0, 0.0, 1.0, 0.0,
                                0.0, 0.0, 0.0, 1.0
                        ],
                        "size": {
                                "width": 0.185,
                                "height": 0.185
                        },
                        "pattern": [
                            0,0,0,1,1,1,
                                1,0,0,0,1,1,
                                1,1,0,1,1,1,
                                0,1,1,0,0,0,
                                0,0,1,0,1,0,
                                1,0,0,1,1,0
                        ]
                }
        },
        "trackable 2":{
                "type": 3,
                "data":{
                        "url": "qrcode_artwin.png",
                        "transform3D": [
                                1.0, 0.0, 0.0, 0.0,
                                0.0, 1.0, 0.0, 0.0,
                                0.0, 0.0, 1.0, 0.0,
                                0.0, 0.0, 0.0, 1.0
                        ],
                        "size": {
                                "width": 0.106,
                                "height": 0.106
                        },
                        "code": "ARTWIN"
                }
        }
}
